Metadata-Version: 2.1
Name: storegames-scraper
Version: 1.0.0
Summary: A python library to scrape data on storegames automatically.
Home-page: https://datakund.com
Author: DataKund
Author-email: datakund@gmail.com
License: Apache License 2.0
Keywords: storegames python bot_studio scraper data web-scraping
Platform: UNKNOWN
